<?xml version="1.0" encoding="utf-8"?>
<annotation><folder>[underwater photo]</folder><filename>bundle of ropes_046_05816.jpg</filename><path>../../[image]/[underwater photo]/bundle of ropes_046_05816.jpg</path><size><width>1920</width><height>1080</height><depth>3</depth></size><commoninfo><datasetname>underwater photo dataset</datasetname><createdate>2020-11-26 15:24:35.0</createdate></commoninfo><metainfo><device>Cannon EOS 100D</device><location><name>Daejin Port</name><latitude><DMS></DMS><DMM></DMM><DD>38.500066</DD></latitude><longitude><DMS></DMS><DMM></DMM><DD>128.428822</DD></longitude></location><depth-of-water></depth-of-water><temperature></temperature><NTU></NTU></metainfo><object><name>bundle of ropes</name><bndbox><xmin>947.8124999999994</xmin><ymin>779.5075479410905</ymin><xmax>1493.4931979138473</xmax><ymax>936.7501424900573</ymax><width>545.6806979138479</width><height>157.24259454896685</height></bndbox><grade>A</grade></object><object><name>bundle of ropes</name><bndbox><xmin>816.5625</xmin><ymin>196.38586956521743</ymin><xmax>974.0625</xmax><ymax>817.03125</ymax><width>157.5</width><height>620.6453804347825</height></bndbox><grade>A</grade></object></annotation>