<?xml version="1.0" encoding="utf-8"?>
<annotation><folder>[underwater photo]</folder><filename>circular fish trap_047_00030.jpg</filename><path>../../[image]/[underwater photo]/circular fish trap_047_00030.jpg</path><size><width>1920</width><height>1080</height><depth>3</depth></size><commoninfo><datasetname>underwater photo dataset</datasetname><createdate>2020-11-26 17:28:26.0</createdate></commoninfo><metainfo><device>Cannon EOS 100D</device><location><name>Jiksan Port</name><latitude><DMS></DMS><DMM></DMM><DD>36.724630</DD></latitude><longitude><DMS></DMS><DMM></DMM><DD>129.474399</DD></longitude></location><depth-of-water></depth-of-water><temperature></temperature><NTU></NTU></metainfo><object><name>circular fish trap</name><bndbox><xmin>342.5947694089409</xmin><ymin>77.35075786914429</ymin><xmax>1643.8920296714532</xmax><ymax>914.2765338223029</ymax><width>1301.2972602625123</width><height>836.9257759531586</height></bndbox><grade>A</grade></object></annotation>