<?xml version="1.0" encoding="utf-8"?>
<annotation><folder>[underwater photo]</folder><filename>circular fish trap_bundle of ropes_047_01461.jpg</filename><path>../../[image]/[underwater photo]/circular fish trap_bundle of ropes_047_01461.jpg</path><size><width>1920</width><height>1080</height><depth>3</depth></size><commoninfo><datasetname>underwater photo dataset</datasetname><createdate>2020-11-26 17:28:26.0</createdate></commoninfo><metainfo><device>Cannon EOS 100D</device><location><name>Jiksan Port</name><latitude><DMS></DMS><DMM></DMM><DD>36.724630</DD></latitude><longitude><DMS></DMS><DMM></DMM><DD>129.474399</DD></longitude></location><depth-of-water></depth-of-water><temperature></temperature><NTU></NTU></metainfo><object><name>circular fish trap</name><bndbox><xmin>738.1249523162842</xmin><ymin>25.351556539535522</ymin><xmax>1196.5624523162842</xmax><ymax>872.8515565395355</ymax><width>458.4375</width><height>847.5</height></bndbox><grade>A</grade></object><object><name>bundle of ropes</name><bndbox><xmin>583.4374523162842</xmin><ymin>479.5750660121265</ymin><xmax>738.7563907174242</xmax><ymax>778.1640565395355</ymax><width>155.31893840114003</width><height>298.588990527409</height></bndbox><grade>A</grade></object></annotation>