<?xml version="1.0" encoding="utf-8"?>
<annotation><folder>[underwater photo]</folder><filename>circular fish trap_029_00547.jpg</filename><path>../../[image]/[underwater photo]/circular fish trap_029_00547.jpg</path><size><width>1920</width><height>1080</height><depth>3</depth></size><commoninfo><datasetname>underwater photo dataset</datasetname><createdate>2021-01-24 23:52:18.0</createdate></commoninfo><metainfo><device>Cannon EOS 100D</device><location><name>Sokcho Port</name><latitude><DMS></DMS><DMM></DMM><DD>38.208858</DD></latitude><longitude><DMS></DMS><DMM></DMM><DD>128.598288</DD></longitude></location><depth-of-water></depth-of-water><temperature></temperature><NTU></NTU></metainfo><object><name>circular fish trap</name><bndbox><xmin>0.0</xmin><ymin>310.9246323804003</ymin><xmax>1920.0</xmax><ymax>988.74755859375</ymax><width>1920.0</width><height>677.8229262133498</height></bndbox><grade>A</grade></object></annotation>