<?xml version="1.0" encoding="utf-8"?>
<annotation><folder>[underwater photo]</folder><filename>circular fish trap_bundle of ropes_045_04637.jpg</filename><path>../../[image]/[underwater photo]/circular fish trap_bundle of ropes_045_04637.jpg</path><size><width>1920</width><height>1080</height><depth>3</depth></size><commoninfo><datasetname>underwater photo dataset</datasetname><createdate>2020-11-17 09:10:34.0</createdate></commoninfo><metainfo><device>Cannon EOS 100D</device><location><name>Chuksan Port</name><latitude><DMS></DMS><DMM></DMM><DD>36.509941</DD></latitude><longitude><DMS></DMS><DMM></DMM><DD>129.450485</DD></longitude></location><depth-of-water></depth-of-water><temperature></temperature><NTU></NTU></metainfo><object><name>circular fish trap</name><bndbox><xmin>830.1923076923076</xmin><ymin>402.65625</ymin><xmax>1487.8846153846152</xmax><ymax>934.8317307692308</ymax><width>657.6923076923076</width><height>532.1754807692308</height></bndbox><grade>A</grade></object><object><name>bundle of ropes</name><bndbox><xmin>957.9957150156878</xmin><ymin>658.2966682277774</ymin><xmax>1474.978091613099</xmax><ymax>1037.0869646336353</ymax><width>516.9823765974112</width><height>378.7902964058578</height></bndbox><grade>A</grade></object><object><name>rope</name><bndbox><xmin>1431.9617705933497</xmin><ymin>0.0</ymin><xmax>1768.7964705637985</xmax><ymax>527.5188792554148</ymax><width>336.8346999704488</width><height>527.5188792554148</height></bndbox><grade>A</grade></object></annotation>