<?xml version="1.0" encoding="utf-8"?>
<annotation><folder>[underwater photo]</folder><filename>circular fish trap_004_00462.jpg</filename><path>../../[image]/[underwater photo]/circular fish trap_004_00462.jpg</path><size><width>1280</width><height>720</height><depth>3</depth></size><commoninfo><datasetname>underwater photo dataset</datasetname><createdate>2020-11-17 09:10:05.0</createdate></commoninfo><metainfo><device>Cannon EOS 100D</device><location><name>Guryongpo</name><latitude><DMS></DMS><DMM></DMM><DD>35.987252</DD></latitude><longitude><DMS></DMS><DMM></DMM><DD>129.556157</DD></longitude></location><depth-of-water></depth-of-water><temperature></temperature><NTU></NTU></metainfo><object><name>circular fish trap</name><bndbox><xmin>255.625</xmin><ymin>53.4375</ymin><xmax>1050.6308593749998</xmax><ymax>682.1875</ymax><width>795.0058593749998</width><height>628.75</height></bndbox><grade>A</grade></object></annotation>