<?xml version="1.0" encoding="utf-8"?>
<annotation><folder>[underwater photo]</folder><filename>circular fish trap_bundle of rope_042_09579.jpg</filename><path>../../[image]/[underwater photo]/circular fish trap_bundle of rope_042_09579.jpg</path><size><width>1920</width><height>1080</height><depth>3</depth></size><commoninfo><datasetname>underwater photo dataset</datasetname><createdate>2021-04-20 13:40:01.0</createdate></commoninfo><metainfo><device>Cannon EOS 100D</device><location><name>Ganggu Port</name><latitude><DMS></DMS><DMM></DMM><DD>36.358498</DD></latitude><longitude><DMS></DMS><DMM></DMM><DD>129.394431</DD></longitude></location><depth-of-water></depth-of-water><temperature></temperature><NTU></NTU></metainfo><object><name>circular fish trap</name><bndbox><xmin>509.72956730769243</xmin><ymin>101.1328125</ymin><xmax>1446.778846153846</xmax><ymax>750.3966346153846</ymax><width>937.0492788461536</width><height>649.2638221153846</height></bndbox><grade>A</grade></object><object><name>bundle of rope</name><bndbox><xmin>1503.75</xmin><ymin>297.2265565395355</ymin><xmax>1920.0</xmax><ymax>965.1953065395355</ymax><width>416.25</width><height>667.96875</height></bndbox><grade>A</grade></object></annotation>