<?xml version="1.0" encoding="utf-8"?>
<annotation><folder>[underwater photo]</folder><filename>eel fish trap_bundle of ropes_004_02099.jpg</filename><path>../../[image]/[underwater photo]/eel fish trap_bundle of ropes_004_02099.jpg</path><size><width>1920</width><height>1080</height><depth>3</depth></size><commoninfo><datasetname>underwater photo dataset</datasetname><createdate>2021-01-05 23:06:42.0</createdate></commoninfo><metainfo><device>Cannon EOS 100D</device><location><name>Guryongpo</name><latitude><DMS></DMS><DMM></DMM><DD>35.987252</DD></latitude><longitude><DMS></DMS><DMM></DMM><DD>129.556157</DD></longitude></location><depth-of-water></depth-of-water><temperature></temperature><NTU></NTU></metainfo><object><name>eel fish trap</name><bndbox><xmin>593.203125</xmin><ymin>0.0</ymin><xmax>1752.421875</xmax><ymax>405.8203125</ymax><width>1159.21875</width><height>405.8203125</height></bndbox><grade>A</grade></object><object><name>eel fish trap</name><bndbox><xmin>192.2031772575251</xmin><ymin>482.9818143812707</ymin><xmax>1916.2499999999998</xmax><ymax>857.734225335249</ymax><width>1724.0468227424747</width><height>374.7524109539783</height></bndbox><grade>A</grade></object><object><name>bundle of ropes</name><bndbox><xmin>177.21935546914793</xmin><ymin>386.43342951267186</ymin><xmax>495.97512819796</xmax><ymax>695.2773797064294</ymax><width>318.7557727288121</width><height>308.84395019375756</height></bndbox><grade>A</grade></object></annotation>