<?xml version="1.0" encoding="utf-8"?>
<annotation><folder>[underwater photo]</folder><filename>eel fish trap_rope_047_03200.jpg</filename><path>../../[image]/[underwater photo]/eel fish trap_rope_047_03200.jpg</path><size><width>1920</width><height>1080</height><depth>3</depth></size><commoninfo><datasetname>underwater photo dataset</datasetname><createdate>2020-11-26 17:35:55.0</createdate></commoninfo><metainfo><device>Cannon EOS 100D</device><location><name>Jiksan Port</name><latitude><DMS></DMS><DMM></DMM><DD>36.724630</DD></latitude><longitude><DMS></DMS><DMM></DMM><DD>129.474399</DD></longitude></location><depth-of-water></depth-of-water><temperature></temperature><NTU></NTU></metainfo><object><name>eel fish trap</name><bndbox><xmin>497.8125</xmin><ymin>278.90625</ymin><xmax>1470.9482965451057</xmax><ymax>600.3515625</ymax><width>973.1357965451057</width><height>321.4453125</height></bndbox><grade>A</grade></object><object><name>rope</name><bndbox><xmin>1407.1875</xmin><ymin>381.6666666666665</ymin><xmax>1650.3285256410259</xmax><ymax>497.2916666666666</ymax><width>243.14102564102586</width><height>115.62500000000006</height></bndbox><grade>A</grade></object></annotation>