<?xml version="1.0" encoding="utf-8"?>
<annotation><folder>[underwater photo]</folder><filename>eel fish trap_rope_tire_047_03239.jpg</filename><path>../../[image]/[underwater photo]/eel fish trap_rope_tire_047_03239.jpg</path><size><width>1280</width><height>720</height><depth>3</depth></size><commoninfo><datasetname>underwater photo dataset</datasetname><createdate>2021-01-05 23:01:00.0</createdate></commoninfo><metainfo><device>Cannon EOS 100D</device><location><name>Jiksan Port</name><latitude><DMS></DMS><DMM></DMM><DD>36.724630</DD></latitude><longitude><DMS></DMS><DMM></DMM><DD>129.474399</DD></longitude></location><depth-of-water></depth-of-water><temperature></temperature><NTU></NTU></metainfo><object><name>eel fish trap</name><bndbox><xmin>222.03125000000003</xmin><ymin>479.921875</ymin><xmax>925.15625</xmax><ymax>720.0</ymax><width>703.125</width><height>240.078125</height></bndbox><grade>A</grade></object><object><name>rope</name><bndbox><xmin>736.1309523809526</xmin><ymin>288.33581349206355</ymin><xmax>854.8809523809526</xmax><ymax>505.5679563492064</ymax><width>118.75</width><height>217.23214285714283</height></bndbox><grade>A</grade></object><object><name>tire</name><bndbox><xmin>0.0</xmin><ymin>0.0</ymin><xmax>806.414067009813</xmax><ymax>619.296875</ymax><width>806.414067009813</width><height>619.296875</height></bndbox><grade>A</grade></object></annotation>