<?xml version="1.0" encoding="utf-8"?>
<annotation><folder>[underwater photo]</folder><filename>eel fish trap_rope_047_00970.jpg</filename><path>../../[image]/[underwater photo]/eel fish trap_rope_047_00970.jpg</path><size><width>1920</width><height>1080</height><depth>3</depth></size><commoninfo><datasetname>underwater photo dataset</datasetname><createdate>2020-11-26 17:37:30.0</createdate></commoninfo><metainfo><device>Cannon EOS 100D</device><location><name>Jiksan Port</name><latitude><DMS></DMS><DMM></DMM><DD>36.724630</DD></latitude><longitude><DMS></DMS><DMM></DMM><DD>129.474399</DD></longitude></location><depth-of-water></depth-of-water><temperature></temperature><NTU></NTU></metainfo><object><name>eel fish trap</name><bndbox><xmin>414.4083605901579</xmin><ymin>318.88010477816016</ymin><xmax>1626.7450938798338</xmax><ymax>728.0538802656517</ymax><width>1212.336733289676</width><height>409.1737754874916</height></bndbox><grade>A</grade></object><object><name>rope</name><bndbox><xmin>275.38131929992363</xmin><ymin>344.19277980106983</ymin><xmax>539.7363848728155</xmax><ymax>526.3875397925981</ymax><width>264.3550655728919</width><height>182.19475999152826</height></bndbox><grade>A</grade></object></annotation>