<?xml version="1.0" encoding="utf-8"?>
<annotation><folder>[underwater photo]</folder><filename>eel fish trap_rectangular fish trap_047_00696.jpg</filename><path>../../[image]/[underwater photo]/eel fish trap_rectangular fish trap_047_00696.jpg</path><size><width>1920</width><height>1080</height><depth>3</depth></size><commoninfo><datasetname>underwater photo dataset</datasetname><createdate>2021-01-05 23:00:59.0</createdate></commoninfo><metainfo><device>Cannon EOS 100D</device><location><name>Jiksan Port</name><latitude><DMS></DMS><DMM></DMM><DD>36.724630</DD></latitude><longitude><DMS></DMS><DMM></DMM><DD>129.474399</DD></longitude></location><depth-of-water></depth-of-water><temperature></temperature><NTU></NTU></metainfo><object><name>eel fish trap</name><bndbox><xmin>0.0</xmin><ymin>462.0703125</ymin><xmax>356.25</xmax><ymax>1080.0</ymax><width>356.25</width><height>617.9296875</height></bndbox><grade>A</grade></object><object><name>rectangular fish trap</name><bndbox><xmin>295.54687500000045</xmin><ymin>124.5703125</ymin><xmax>1689.9572683255417</xmax><ymax>956.5024038461539</ymax><width>1394.4103933255412</width><height>831.9320913461539</height></bndbox><grade>A</grade></object></annotation>