<?xml version="1.0" encoding="utf-8"?>
<annotation><folder>[underwater photo]</folder><filename>eel fish trap_circular fish trap_004_02073.jpg</filename><path>../../[image]/[underwater photo]/eel fish trap_circular fish trap_004_02073.jpg</path><size><width>1280</width><height>720</height><depth>3</depth></size><commoninfo><datasetname>underwater photo dataset</datasetname><createdate>2021-01-05 23:00:50.0</createdate></commoninfo><metainfo><device>Cannon EOS 100D</device><location><name>Guryongpo</name><latitude><DMS></DMS><DMM></DMM><DD>35.987252</DD></latitude><longitude><DMS></DMS><DMM></DMM><DD>129.556157</DD></longitude></location><depth-of-water></depth-of-water><temperature></temperature><NTU></NTU></metainfo><object><name>eel fish trap</name><bndbox><xmin>154.375</xmin><ymin>340.9375</ymin><xmax>851.875</xmax><ymax>720.0</ymax><width>697.5</width><height>379.0625</height></bndbox><grade>A</grade></object><object><name>circular fish trap</name><bndbox><xmin>106.875</xmin><ymin>-0.3125</ymin><xmax>678.125</xmax><ymax>389.6875</ymax><width>571.25</width><height>390.0</height></bndbox><grade>A</grade></object></annotation>