<?xml version="1.0" encoding="utf-8"?>
<annotation><folder>[underwater photo]</folder><filename>fish net_029_02211.jpg</filename><path>../../[image]/[underwater photo]/fish net_029_02211.jpg</path><size><width>640</width><height>480</height><depth>3</depth></size><commoninfo><datasetname>underwater photo dataset</datasetname><createdate>2021-01-24 23:53:29.0</createdate></commoninfo><metainfo><device>Cannon EOS 100D</device><location><name>Sokcho Port</name><latitude><DMS></DMS><DMM></DMM><DD>38.208858</DD></latitude><longitude><DMS></DMS><DMM></DMM><DD>128.598288</DD></longitude></location><depth-of-water></depth-of-water><temperature></temperature><NTU></NTU></metainfo><object><name>fish net</name><bndbox><xmin>0.0</xmin><ymin>0.0</ymin><xmax>640.0</xmax><ymax>480.00000000000006</ymax><width>640.0</width><height>480.00000000000006</height></bndbox><grade>A</grade></object></annotation>