<?xml version="1.0" encoding="utf-8"?>
<annotation><folder>[underwater photo]</folder><filename>fish net_048_00356.jpg</filename><path>../../[image]/[underwater photo]/fish net_048_00356.jpg</path><size><width>1920</width><height>1080</height><depth>3</depth></size><commoninfo><datasetname>underwater photo dataset</datasetname><createdate>2021-02-02 06:40:41.0</createdate></commoninfo><metainfo><device>Cannon EOS 100D</device><location><name>Sacheon New Port</name><latitude><DMS></DMS><DMM></DMM><DD>34.923494</DD></latitude><longitude><DMS></DMS><DMM></DMM><DD>128.083641</DD></longitude></location><depth-of-water></depth-of-water><temperature></temperature><NTU></NTU></metainfo><object><name>fish net</name><bndbox><xmin>337.33882238278676</xmin><ymin>178.85904105623507</ymin><xmax>977.1634615384617</xmax><ymax>572.2355769230774</ymax><width>639.824639155675</width><height>393.3765358668423</height></bndbox><grade>A</grade></object></annotation>