<?xml version="1.0" encoding="utf-8"?>
<annotation><folder>[underwater photo]</folder><filename>fish net_bundle of ropes_042_00194.jpg</filename><path>../../[image]/[underwater photo]/fish net_bundle of ropes_042_00194.jpg</path><size><width>1920</width><height>1080</height><depth>3</depth></size><commoninfo><datasetname>underwater photo dataset</datasetname><createdate>2020-11-26 15:30:05.0</createdate></commoninfo><metainfo><device>Cannon EOS 100D</device><location><name>Ganggu Port</name><latitude><DMS></DMS><DMM></DMM><DD>36.358498</DD></latitude><longitude><DMS></DMS><DMM></DMM><DD>129.394431</DD></longitude></location><depth-of-water></depth-of-water><temperature></temperature><NTU></NTU></metainfo><object><name>fish net</name><bndbox><xmin>481.69070512820525</xmin><ymin>0.0</ymin><xmax>1509.7424479862655</xmax><ymax>880.9415064102565</ymax><width>1028.0517428580602</width><height>880.9415064102565</height></bndbox><grade>A</grade></object><object><name>bundle of ropes</name><bndbox><xmin>1399.5257256330622</xmin><ymin>257.8125</ymin><xmax>1542.354966173584</xmax><ymax>746.0322229853482</ymax><width>142.82924054052182</width><height>488.2197229853482</height></bndbox><grade>A</grade></object></annotation>