<?xml version="1.0" encoding="utf-8"?>
<annotation><folder>[underwater photo]</folder><filename>fish net_bundle of ropes_042_01988.jpg</filename><path>../../[image]/[underwater photo]/fish net_bundle of ropes_042_01988.jpg</path><size><width>1920</width><height>1080</height><depth>3</depth></size><commoninfo><datasetname>underwater photo dataset</datasetname><createdate>2020-11-26 15:30:45.0</createdate></commoninfo><metainfo><device>Cannon EOS 100D</device><location><name>Ganggu Port</name><latitude><DMS></DMS><DMM></DMM><DD>36.358498</DD></latitude><longitude><DMS></DMS><DMM></DMM><DD>129.394431</DD></longitude></location><depth-of-water></depth-of-water><temperature></temperature><NTU></NTU></metainfo><object><name>fish net</name><bndbox><xmin>446.71875000000006</xmin><ymin>127.62419871794873</ymin><xmax>1370.8854495697028</xmax><ymax>879.4831730769231</ymax><width>924.1666995697028</width><height>751.8589743589744</height></bndbox><grade>A</grade></object><object><name>bundle of ropes</name><bndbox><xmin>1196.8028846153848</xmin><ymin>306.6018198287222</ymin><xmax>1801.2900641025647</xmax><ymax>709.2107371794875</ymax><width>604.4871794871799</width><height>402.6089173507653</height></bndbox><grade>A</grade></object></annotation>