<?xml version="1.0" encoding="utf-8"?>
<annotation><folder>[underwater photo]</folder><filename>rectangular fish trap_bundle of ropes_047_01203.jpg</filename><path>../../[image]/[underwater photo]/rectangular fish trap_bundle of ropes_047_01203.jpg</path><size><width>1920</width><height>1080</height><depth>3</depth></size><commoninfo><datasetname>underwater photo dataset</datasetname><createdate>2020-11-26 16:48:16.0</createdate></commoninfo><metainfo><device>Cannon EOS 100D</device><location><name>Jiksan Port</name><latitude><DMS></DMS><DMM></DMM><DD>36.724630</DD></latitude><longitude><DMS></DMS><DMM></DMM><DD>129.474399</DD></longitude></location><depth-of-water></depth-of-water><temperature></temperature><NTU></NTU></metainfo><object><name>rectangular fish trap</name><bndbox><xmin>566.6007022868437</xmin><ymin>108.1640625</ymin><xmax>1638.5125475322893</xmax><ymax>983.0248397435898</ymax><width>1071.9118452454456</width><height>874.8607772435898</height></bndbox><grade>A</grade></object><object><name>bundle of ropes</name><bndbox><xmin>926.015625</xmin><ymin>0.0</ymin><xmax>1100.3907348643538</xmax><ymax>147.3425873882433</ymax><width>174.37510986435382</width><height>147.3425873882433</height></bndbox><grade>A</grade></object></annotation>