<?xml version="1.0" encoding="utf-8"?>
<annotation><folder>[underwater photo]</folder><filename>rope_048_01663.jpg</filename><path>../../[image]/[underwater photo]/rope_048_01663.jpg</path><size><width>1920</width><height>1080</height><depth>3</depth></size><commoninfo><datasetname>underwater photo dataset</datasetname><createdate>2021-02-02 06:36:49.0</createdate></commoninfo><metainfo><device>Cannon EOS 100D</device><location><name>Sacheon New Port</name><latitude><DMS></DMS><DMM></DMM><DD>34.923494</DD></latitude><longitude><DMS></DMS><DMM></DMM><DD>128.083641</DD></longitude></location><depth-of-water></depth-of-water><temperature></temperature><NTU></NTU></metainfo><object><name>rope</name><bndbox><xmin>798.9322757720947</xmin><ymin>467.53905951976776</ymin><xmax>1920.0</xmax><ymax>855.3139661825</ymax><width>1121.0677242279053</width><height>387.7749066627323</height></bndbox><grade>A</grade></object></annotation>