<?xml version="1.0" encoding="utf-8"?>
<annotation><folder>[underwater photo]</folder><filename>rope_010_00099.jpg</filename><path>../../[image]/[underwater photo]/rope_010_00099.jpg</path><size><width>1920</width><height>1080</height><depth>3</depth></size><commoninfo><datasetname>underwater photo dataset</datasetname><createdate>2021-01-05 23:05:10.0</createdate></commoninfo><metainfo><device>Cannon EOS 100D</device><location><name>Uljin-gun</name><latitude><DMS></DMS><DMM></DMM><DD>37.049746</DD></latitude><longitude><DMS></DMS><DMM></DMM><DD>129.420208</DD></longitude></location><depth-of-water></depth-of-water><temperature></temperature><NTU></NTU></metainfo><object><name>rope</name><bndbox><xmin>160.4923582401454</xmin><ymin>0.0</ymin><xmax>1654.0917615154876</xmax><ymax>1080.0</ymax><width>1493.5994032753422</width><height>1080.0</height></bndbox><grade>A</grade></object></annotation>