<?xml version="1.0" encoding="utf-8"?>
<annotation><folder>[underwater photo]</folder><filename>rope_spring fish trap_bundle of ropes_042_10402.jpg</filename><path>../../[image]/[underwater photo]/rope_spring fish trap_bundle of ropes_042_10402.jpg</path><size><width>1920</width><height>1080</height><depth>3</depth></size><commoninfo><datasetname>underwater photo dataset</datasetname><createdate>2021-01-05 23:06:51.0</createdate></commoninfo><metainfo><device>Cannon EOS 100D</device><location><name>Ganggu Port</name><latitude><DMS></DMS><DMM></DMM><DD>36.358498</DD></latitude><longitude><DMS></DMS><DMM></DMM><DD>129.394431</DD></longitude></location><depth-of-water></depth-of-water><temperature></temperature><NTU></NTU></metainfo><object><name>rope</name><bndbox><xmin>672.890625</xmin><ymin>290.9765625</ymin><xmax>1186.8037555741362</xmax><ymax>468.29222408026766</ymax><width>513.9131305741362</width><height>177.31566158026766</height></bndbox><grade>A</grade></object><object><name>spring fish trap</name><bndbox><xmin>335.390625</xmin><ymin>342.5390625</ymin><xmax>1920.0</xmax><ymax>1080.0</ymax><width>1584.609375</width><height>737.4609375</height></bndbox><grade>A</grade></object><object><name>bundle of ropes</name><bndbox><xmin>1240.078125</xmin><ymin>0.0</ymin><xmax>1920.0</xmax><ymax>670.3125</ymax><width>679.921875</width><height>670.3125</height></bndbox><grade>A</grade></object></annotation>