<?xml version="1.0" encoding="utf-8"?>
<annotation><folder>[underwater photo]</folder><filename>rope_029_01260.jpg</filename><path>../../[image]/[underwater photo]/rope_029_01260.jpg</path><size><width>1920</width><height>1080</height><depth>3</depth></size><commoninfo><datasetname>underwater photo dataset</datasetname><createdate>2021-01-24 23:56:58.0</createdate></commoninfo><metainfo><device>Cannon EOS 100D</device><location><name>Sokcho Port</name><latitude><DMS></DMS><DMM></DMM><DD>38.208858</DD></latitude><longitude><DMS></DMS><DMM></DMM><DD>128.598288</DD></longitude></location><depth-of-water></depth-of-water><temperature></temperature><NTU></NTU></metainfo><object><name>rope</name><bndbox><xmin>792.8365384615382</xmin><ymin>110.69711538461539</ymin><xmax>1596.2019230769229</xmax><ymax>420.7932692307693</ymax><width>803.3653846153846</width><height>310.0961538461539</height></bndbox><grade>A</grade></object></annotation>