<?xml version="1.0" encoding="utf-8"?>
<annotation><folder>[underwater photo]</folder><filename>rope_029_01372.jpg</filename><path>../../[image]/[underwater photo]/rope_029_01372.jpg</path><size><width>1920</width><height>1080</height><depth>3</depth></size><commoninfo><datasetname>underwater photo dataset</datasetname><createdate>2021-01-24 23:52:32.0</createdate></commoninfo><metainfo><device>Cannon EOS 100D</device><location><name>Sokcho Port</name><latitude><DMS></DMS><DMM></DMM><DD>38.208858</DD></latitude><longitude><DMS></DMS><DMM></DMM><DD>128.598288</DD></longitude></location><depth-of-water></depth-of-water><temperature></temperature><NTU></NTU></metainfo><object><name>rope</name><bndbox><xmin>712.4686703694856</xmin><ymin>189.9543617614271</ymin><xmax>1100.8836996337002</xmax><ymax>1076.2620192307693</ymax><width>388.4150292642146</width><height>886.3076574693422</height></bndbox><grade>A</grade></object></annotation>