<?xml version="1.0" encoding="utf-8"?>
<annotation><folder>[underwater photo]</folder><filename>spring fish trap_048_00752.jpg</filename><path>../../[image]/[underwater photo]/spring fish trap_048_00752.jpg</path><size><width>1920</width><height>1080</height><depth>3</depth></size><commoninfo><datasetname>underwater photo dataset</datasetname><createdate>2021-02-02 06:38:27.0</createdate></commoninfo><metainfo><device>Cannon EOS 100D</device><location><name>Sacheon New Port</name><latitude><DMS></DMS><DMM></DMM><DD>34.923494</DD></latitude><longitude><DMS></DMS><DMM></DMM><DD>128.083641</DD></longitude></location><depth-of-water></depth-of-water><temperature></temperature><NTU></NTU></metainfo><object><name>spring fish trap</name><bndbox><xmin>517.3550347804979</xmin><ymin>152.54217506115862</ymin><xmax>1333.0279792717274</xmax><ymax>979.9095553331022</ymax><width>815.6729444912295</width><height>827.3673802719436</height></bndbox><grade>A</grade></object></annotation>