<?xml version="1.0" encoding="utf-8"?>
<annotation><folder>[underwater photo]</folder><filename>tire_rope_046_01381.jpg</filename><path>../../[image]/[underwater photo]/tire_rope_046_01381.jpg</path><size><width>1920</width><height>1080</height><depth>3</depth></size><commoninfo><datasetname>underwater photo dataset</datasetname><createdate>2020-11-26 16:16:45.0</createdate></commoninfo><metainfo><device>Cannon EOS 100D</device><location><name>Daejin Port</name><latitude><DMS></DMS><DMM></DMM><DD>38.500066</DD></latitude><longitude><DMS></DMS><DMM></DMM><DD>128.428822</DD></longitude></location><depth-of-water></depth-of-water><temperature></temperature><NTU></NTU></metainfo><object><name>tire</name><bndbox><xmin>347.98295454545416</xmin><ymin>116.57670454545458</ymin><xmax>1589.4902209797042</xmax><ymax>961.3925657675658</ymax><width>1241.5072664342501</width><height>844.8158612221112</height></bndbox><grade>A</grade></object><object><name>rope</name><bndbox><xmin>0.9375</xmin><ymin>586.40625</ymin><xmax>968.4375</xmax><ymax>1080.0</ymax><width>967.5</width><height>493.59375</height></bndbox><grade>A</grade></object><object><name>rope</name><bndbox><xmin>0.0</xmin><ymin>5.15625</ymin><xmax>315.9375</xmax><ymax>278.90625</ymax><width>315.9375</width><height>273.75</height></bndbox><grade>A</grade></object></annotation>