<?xml version="1.0" encoding="utf-8"?>
<annotation><folder>[underwater photo]</folder><filename>tire_029_00910.jpg</filename><path>../../[image]/[underwater photo]/tire_029_00910.jpg</path><size><width>1920</width><height>1080</height><depth>3</depth></size><commoninfo><datasetname>underwater photo dataset</datasetname><createdate>2021-01-24 23:51:47.0</createdate></commoninfo><metainfo><device>Cannon EOS 100D</device><location><name>Sokcho Port</name><latitude><DMS></DMS><DMM></DMM><DD>38.208858</DD></latitude><longitude><DMS></DMS><DMM></DMM><DD>128.598288</DD></longitude></location><depth-of-water></depth-of-water><temperature></temperature><NTU></NTU></metainfo><object><name>tire</name><bndbox><xmin>-1.9531249999999556</xmin><ymin>54.529746093750035</ymin><xmax>1718.359375</xmax><ymax>849.0609960937501</ymax><width>1720.3125</width><height>794.53125</height></bndbox><grade>A</grade></object></annotation>