<?xml version="1.0" encoding="utf-8"?>
<annotation><folder>[underwater photo]</folder><filename>tire_044_05405.jpg</filename><path>../../[image]/[underwater photo]/tire_044_05405.jpg</path><size><width>1280</width><height>720</height><depth>3</depth></size><commoninfo><datasetname>underwater photo dataset</datasetname><createdate>2021-01-05 23:03:25.0</createdate></commoninfo><metainfo><device>Cannon EOS 100D</device><location><name>Jukbyeon Port</name><latitude><DMS></DMS><DMM></DMM><DD>37.055768</DD></latitude><longitude><DMS></DMS><DMM></DMM><DD>129.421697</DD></longitude></location><depth-of-water></depth-of-water><temperature></temperature><NTU></NTU></metainfo><object><name>tire</name><bndbox><xmin>528.28125</xmin><ymin>0.0</ymin><xmax>1093.28125</xmax><ymax>390.0</ymax><width>565.0</width><height>390.0</height></bndbox><grade>A</grade></object><object><name>tire</name><bndbox><xmin>0.0</xmin><ymin>276.875</ymin><xmax>770.46875</xmax><ymax>720.0</ymax><width>770.46875</width><height>443.125</height></bndbox><grade>A</grade></object></annotation>