<?xml version="1.0" encoding="utf-8"?>
<annotation><folder>[underwater photo]</folder><filename>tire_rope_042_10320.jpg</filename><path>../../[image]/[underwater photo]/tire_rope_042_10320.jpg</path><size><width>1920</width><height>1080</height><depth>3</depth></size><commoninfo><datasetname>underwater photo dataset</datasetname><createdate>2020-11-26 16:09:25.0</createdate></commoninfo><metainfo><device>Cannon EOS 100D</device><location><name>Ganggu Port</name><latitude><DMS></DMS><DMM></DMM><DD>36.358498</DD></latitude><longitude><DMS></DMS><DMM></DMM><DD>129.394431</DD></longitude></location><depth-of-water></depth-of-water><temperature></temperature><NTU></NTU></metainfo><object><name>tire</name><bndbox><xmin>441.5705128205127</xmin><ymin>0.0</ymin><xmax>1647.1267229147666</xmax><ymax>943.104967948718</ymax><width>1205.5562100942539</width><height>943.104967948718</height></bndbox><grade>A</grade></object><object><name>rope</name><bndbox><xmin>1209.8822107155302</xmin><ymin>105.58788050612176</ymin><xmax>1613.0072107155302</xmax><ymax>206.03430907755035</ymax><width>403.125</width><height>100.44642857142858</height></bndbox><grade>A</grade></object></annotation>