<?xml version="1.0" encoding="utf-8"?>
<annotation><folder>[underwater photo]</folder><filename>tire_bundle of ropes_045_04949.jpg</filename><path>../../[image]/[underwater photo]/tire_bundle of ropes_045_04949.jpg</path><size><width>1920</width><height>1080</height><depth>3</depth></size><commoninfo><datasetname>underwater photo dataset</datasetname><createdate>2020-11-17 09:12:22.0</createdate></commoninfo><metainfo><device>Cannon EOS 100D</device><location><name>Chuksan Port</name><latitude><DMS></DMS><DMM></DMM><DD>36.509941</DD></latitude><longitude><DMS></DMS><DMM></DMM><DD>129.450485</DD></longitude></location><depth-of-water></depth-of-water><temperature></temperature><NTU></NTU></metainfo><object><name>tire</name><bndbox><xmin>358.86217948717945</xmin><ymin>197.291666666667</ymin><xmax>1477.9326923076924</xmax><ymax>1035.7932692307697</ymax><width>1119.070512820513</width><height>838.5016025641028</height></bndbox><grade>A</grade></object><object><name>bundle of ropes</name><bndbox><xmin>1195.2864583333333</xmin><ymin>332.1874999999995</ymin><xmax>1482.7804487179487</xmax><ymax>759.2708333333333</ymax><width>287.4939903846155</width><height>427.08333333333377</height></bndbox><grade>A</grade></object></annotation>