<?xml version="1.0" encoding="utf-8"?>
<annotation><folder>[underwater photo]</folder><filename>tire_rope_047_03148.jpg</filename><path>../../[image]/[underwater photo]/tire_rope_047_03148.jpg</path><size><width>1920</width><height>1080</height><depth>3</depth></size><commoninfo><datasetname>underwater photo dataset</datasetname><createdate>2020-11-26 16:37:06.0</createdate></commoninfo><metainfo><device>Cannon EOS 100D</device><location><name>Jiksan Port</name><latitude><DMS></DMS><DMM></DMM><DD>36.724630</DD></latitude><longitude><DMS></DMS><DMM></DMM><DD>129.474399</DD></longitude></location><depth-of-water></depth-of-water><temperature></temperature><NTU></NTU></metainfo><object><name>tire</name><bndbox><xmin>320.2466804029304</xmin><ymin>0.3515625000001066</ymin><xmax>1710.9690602673463</xmax><ymax>894.3386561355311</ymax><width>1390.7223798644159</width><height>893.987093635531</height></bndbox><grade>A</grade></object><object><name>rope</name><bndbox><xmin>1538.4695512820513</xmin><ymin>494.8828125</ymin><xmax>1897.734375</xmax><ymax>725.8774038461539</ymax><width>359.26482371794873</width><height>230.99459134615392</height></bndbox><grade>A</grade></object></annotation>