<?xml version="1.0" encoding="utf-8"?>
<annotation><folder>[underwater photo]</folder><filename>tire_046_01662.jpg</filename><path>../../[image]/[underwater photo]/tire_046_01662.jpg</path><size><width>1920</width><height>1080</height><depth>3</depth></size><commoninfo><datasetname>underwater photo dataset</datasetname><createdate>2020-11-26 16:20:06.0</createdate></commoninfo><metainfo><device>Cannon EOS 100D</device><location><name>Daejin Port</name><latitude><DMS></DMS><DMM></DMM><DD>38.500066</DD></latitude><longitude><DMS></DMS><DMM></DMM><DD>128.428822</DD></longitude></location><depth-of-water></depth-of-water><temperature></temperature><NTU></NTU></metainfo><object><name>tire</name><bndbox><xmin>320.33900203057794</xmin><ymin>53.67301968864467</ymin><xmax>1593.9175357918207</xmax><ymax>992.9346955128207</ymax><width>1273.5785337612429</width><height>939.261675824176</height></bndbox><grade>A</grade></object></annotation>