<?xml version="1.0" encoding="utf-8"?>
<annotation><folder>[underwater photo]</folder><filename>tire_wood_042_09319.jpg</filename><path>../../[image]/[underwater photo]/tire_wood_042_09319.jpg</path><size><width>1920</width><height>1080</height><depth>3</depth></size><commoninfo><datasetname>underwater photo dataset</datasetname><createdate>2020-11-26 16:01:11.0</createdate></commoninfo><metainfo><device>Cannon EOS 100D</device><location><name>Ganggu Port</name><latitude><DMS></DMS><DMM></DMM><DD>36.358498</DD></latitude><longitude><DMS></DMS><DMM></DMM><DD>129.394431</DD></longitude></location><depth-of-water></depth-of-water><temperature></temperature><NTU></NTU></metainfo><object><name>tire</name><bndbox><xmin>454.5312023162842</xmin><ymin>270.66405951976776</ymin><xmax>1303.4374523162842</xmax><ymax>737.5390595197678</ymax><width>848.90625</width><height>466.875</height></bndbox><grade>A</grade></object><object><name>wood</name><bndbox><xmin>0.0</xmin><ymin>459.7265625</ymin><xmax>492.4218749999999</xmax><ymax>1080.0</ymax><width>492.4218749999999</width><height>620.2734375</height></bndbox><grade>A</grade></object></annotation>