<?xml version="1.0" encoding="utf-8"?>
<annotation><folder>[underwater photo]</folder><filename>tire_044_05540.jpg</filename><path>../../[image]/[underwater photo]/tire_044_05540.jpg</path><size><width>1920</width><height>1080</height><depth>3</depth></size><commoninfo><datasetname>underwater photo dataset</datasetname><createdate>2020-11-17 09:12:01.0</createdate></commoninfo><metainfo><device>Cannon EOS 100D</device><location><name>Jukbyeon Port</name><latitude><DMS></DMS><DMM></DMM><DD>37.055768</DD></latitude><longitude><DMS></DMS><DMM></DMM><DD>129.421697</DD></longitude></location><depth-of-water></depth-of-water><temperature></temperature><NTU></NTU></metainfo><object><name>tire</name><bndbox><xmin>530.9745762711865</xmin><ymin>33.13466830617675</ymin><xmax>1424.067833231621</xmax><ymax>671.9703756045026</ymax><width>893.0932569604346</width><height>638.8357072983258</height></bndbox><grade>A</grade></object></annotation>