<?xml version="1.0" encoding="utf-8"?>
<annotation><folder>[underwater photo]</folder><filename>tire_046_03810.jpg</filename><path>../../[image]/[underwater photo]/tire_046_03810.jpg</path><size><width>1920</width><height>1080</height><depth>3</depth></size><commoninfo><datasetname>underwater photo dataset</datasetname><createdate>2020-11-26 16:22:21.0</createdate></commoninfo><metainfo><device>Cannon EOS 100D</device><location><name>Daejin Port</name><latitude><DMS></DMS><DMM></DMM><DD>38.500066</DD></latitude><longitude><DMS></DMS><DMM></DMM><DD>128.428822</DD></longitude></location><depth-of-water></depth-of-water><temperature></temperature><NTU></NTU></metainfo><object><name>tire</name><bndbox><xmin>656.737930093867</xmin><ymin>109.01611374801632</ymin><xmax>1561.533066384309</xmax><ymax>861.8085154775939</ymax><width>904.795136290442</width><height>752.7924017295776</height></bndbox><grade>A</grade></object></annotation>