<?xml version="1.0" encoding="utf-8"?>
<annotation><folder>[underwater photo]</folder><filename>wood_048_01480.jpg</filename><path>../../[image]/[underwater photo]/wood_048_01480.jpg</path><size><width>1920</width><height>1080</height><depth>3</depth></size><commoninfo><datasetname>underwater photo dataset</datasetname><createdate>2021-02-02 06:44:38.0</createdate></commoninfo><metainfo><device>Cannon EOS 100D</device><location><name>Sacheon New Port</name><latitude><DMS></DMS><DMM></DMM><DD>34.923494</DD></latitude><longitude><DMS></DMS><DMM></DMM><DD>128.083641</DD></longitude></location><depth-of-water></depth-of-water><temperature></temperature><NTU></NTU></metainfo><object><name>wood</name><bndbox><xmin>846.328125</xmin><ymin>122.2265625</ymin><xmax>1380.703125</xmax><ymax>991.7578125</ymax><width>534.375</width><height>869.53125</height></bndbox><grade>A</grade></object></annotation>