<?xml version="1.0" encoding="utf-8"?>
<annotation><folder>[underwater photo]</folder><filename>wood_004_04678.jpg</filename><path>../../[image]/[underwater photo]/wood_004_04678.jpg</path><size><width>1920</width><height>1080</height><depth>3</depth></size><commoninfo><datasetname>underwater photo dataset</datasetname><createdate>2021-01-05 23:01:58.0</createdate></commoninfo><metainfo><device>Cannon EOS 100D</device><location><name>Guryongpo</name><latitude><DMS></DMS><DMM></DMM><DD>35.987252</DD></latitude><longitude><DMS></DMS><DMM></DMM><DD>129.556157</DD></longitude></location><depth-of-water></depth-of-water><temperature></temperature><NTU></NTU></metainfo><object><name>wood</name><bndbox><xmin>767.5244217927436</xmin><ymin>199.66460858185997</ymin><xmax>1330.3125</xmax><ymax>1080.0</ymax><width>562.7880782072564</width><height>880.33539141814</height></bndbox><grade>A</grade></object></annotation>