<?xml version="1.0" encoding="utf-8"?>
<annotation><folder>[underwater photo]</folder><filename>wood_048_02457.jpg</filename><path>../../[image]/[underwater photo]/wood_048_02457.jpg</path><size><width>1920</width><height>1080</height><depth>3</depth></size><commoninfo><datasetname>underwater photo dataset</datasetname><createdate>2021-02-02 06:45:28.0</createdate></commoninfo><metainfo><device>Cannon EOS 100D</device><location><name>Sacheon New Port</name><latitude><DMS></DMS><DMM></DMM><DD>34.923494</DD></latitude><longitude><DMS></DMS><DMM></DMM><DD>128.083641</DD></longitude></location><depth-of-water></depth-of-water><temperature></temperature><NTU></NTU></metainfo><object><name>wood</name><bndbox><xmin>649.453125</xmin><ymin>312.0703125</ymin><xmax>1329.140625</xmax><ymax>818.3203125</ymax><width>679.6875</width><height>506.25</height></bndbox><grade>A</grade></object><object><name>wood</name><bndbox><xmin>841.640625</xmin><ymin>363.6328125</ymin><xmax>1830.703125</xmax><ymax>665.9765625</ymax><width>989.0625</width><height>302.34375</height></bndbox><grade>A</grade></object></annotation>