<?xml version="1.0" encoding="utf-8"?>
<annotation><folder>[underwater photo]</folder><filename>wood_048_01417.jpg</filename><path>../../[image]/[underwater photo]/wood_048_01417.jpg</path><size><width>1920</width><height>1080</height><depth>3</depth></size><commoninfo><datasetname>underwater photo dataset</datasetname><createdate>2021-02-02 06:44:49.0</createdate></commoninfo><metainfo><device>Cannon EOS 100D</device><location><name>Sacheon New Port</name><latitude><DMS></DMS><DMM></DMM><DD>34.923494</DD></latitude><longitude><DMS></DMS><DMM></DMM><DD>128.083641</DD></longitude></location><depth-of-water></depth-of-water><temperature></temperature><NTU></NTU></metainfo><object><name>wood</name><bndbox><xmin>653.6156002988702</xmin><ymin>354.55387878813343</ymin><xmax>1094.3954919780601</xmax><ymax>1080.0</ymax><width>440.77989167919</width><height>725.4461212118665</height></bndbox><grade>A</grade></object></annotation>