<?xml version="1.0" encoding="utf-8"?>
<annotation><folder>[underwater photo]</folder><filename>wood_004_02665.jpg</filename><path>../../[image]/[underwater photo]/wood_004_02665.jpg</path><size><width>1920</width><height>1080</height><depth>3</depth></size><commoninfo><datasetname>underwater photo dataset</datasetname><createdate>2020-11-17 09:10:47.0</createdate></commoninfo><metainfo><device>Cannon EOS 100D</device><location><name>Guryongpo</name><latitude><DMS></DMS><DMM></DMM><DD>35.987252</DD></latitude><longitude><DMS></DMS><DMM></DMM><DD>129.556157</DD></longitude></location><depth-of-water></depth-of-water><temperature></temperature><NTU></NTU></metainfo><object><name>wood</name><bndbox><xmin>211.56828703703695</xmin><ymin>484.65856481481495</ymin><xmax>1665.009759110039</xmax><ymax>1015.2246022224426</ymax><width>1453.4414720730022</width><height>530.5660374076276</height></bndbox><grade>A</grade></object></annotation>