<?xml version="1.0" encoding="utf-8"?>
<annotation><folder>[underwater photo]</folder><filename>wood_042_01658.jpg</filename><path>../../[image]/[underwater photo]/wood_042_01658.jpg</path><size><width>1920</width><height>1080</height><depth>3</depth></size><commoninfo><datasetname>underwater photo dataset</datasetname><createdate>2020-11-26 15:26:01.0</createdate></commoninfo><metainfo><device>Cannon EOS 100D</device><location><name>Ganggu Port</name><latitude><DMS></DMS><DMM></DMM><DD>36.358498</DD></latitude><longitude><DMS></DMS><DMM></DMM><DD>129.394431</DD></longitude></location><depth-of-water></depth-of-water><temperature></temperature><NTU></NTU></metainfo><object><name>wood</name><bndbox><xmin>376.33593409967693</xmin><ymin>366.97300029032806</ymin><xmax>1589.3297520852636</xmax><ymax>636.5232826885789</ymax><width>1212.9938179855867</width><height>269.55028239825083</height></bndbox><grade>A</grade></object></annotation>